flash_softdtw/autograd.py
flash_softdtw/concrt140.dll
flash_softdtw/convert.py
flash_softdtw/features.py
flash_softdtw/flash_softdtw_pybind.cp313-win_amd64.pyd
flash_softdtw/flash_softdtw_pybind.pyi
flash_softdtw/manhattan_distance.py
flash_softdtw/module.py
flash_softdtw/msvcp140.dll
flash_softdtw/msvcp140_1.dll
flash_softdtw/msvcp140_2.dll
flash_softdtw/msvcp140_atomic_wait.dll
flash_softdtw/msvcp140_codecvt_ids.dll
flash_softdtw/py.typed
flash_softdtw/softdtw.py
flash_softdtw/utils.py
flash_softdtw/vcruntime140.dll
flash_softdtw/vcruntime140_1.dll
flash_softdtw/__init__.py
flash_softdtw-0.1.9.dist-info/DELVEWHEEL
flash_softdtw-0.1.9.dist-info/METADATA
flash_softdtw-0.1.9.dist-info/RECORD
flash_softdtw-0.1.9.dist-info/WHEEL
flash_softdtw.libs/msvcp140-173e0efa998dc33612e518408bfd190c.dll
