Metadata-Version: 2.2
Name: flash-softdtw
Version: 0.1.9
Summary: Add your description here
Requires-Python: >=3.10
Requires-Dist: numpy>=2.3.1
Requires-Dist: torch>=2.6.0
